django_easy_cache-0.1.0.dist-info/licenses/LICENSE.md
easy_cache/__init__.py
easy_cache/admin.py
easy_cache/apps.py
easy_cache/config.py
easy_cache/exceptions.py
easy_cache/models.py
easy_cache/decorators/__init__.py
easy_cache/decorators/base.py
easy_cache/decorators/cron.py
easy_cache/decorators/easy_cache.py
easy_cache/decorators/time.py
easy_cache/management/__init__.py
easy_cache/management/commands/__init__.py
easy_cache/management/commands/easy_cache.py
easy_cache/migrations/0001_initial.py
easy_cache/migrations/0002_cacheentry_cache_type_and_more.py
easy_cache/migrations/__init__.py
easy_cache/services/__init__.py
easy_cache/services/analytics_tracker.py
easy_cache/services/key_generator.py
easy_cache/services/storage_handler.py
easy_cache/utils/__init__.py
easy_cache/utils/format_duration_ms.py
easy_cache/utils/format_time_left.py
easy_cache/utils/validation.py
django_easy_cache-0.1.0.dist-info/METADATA
django_easy_cache-0.1.0.dist-info/WHEEL
django_easy_cache-0.1.0.dist-info/top_level.txt
django_easy_cache-0.1.0.dist-info/RECORD
