Metadata-Version: 2.4
Name: django-easy-cache
Version: 0.1.0
Author-email: Peter Bergen <bergen@peterbergen-softwaresolutions.de>
License-Expression: MIT
Project-URL: Homepage, https://github.com/pbergen/django-easy-cache/
Project-URL: Documentation, https://django-easy-cache.readthedocs.io/en/latest/index.html
Project-URL: Bugtracker, https://github.com/pbergen/django-easy-cache/issues
Project-URL: Changelog, https://django-easy-cache.readthedocs.io/en/latest/features/changelog.html
Keywords: django,cache,caching,performance
Classifier: Development Status :: 3 - Alpha
Classifier: Environment :: Web Environment
Classifier: Framework :: Django
Classifier: Framework :: Django :: 4.2
Classifier: Framework :: Django :: 5.1
Classifier: Framework :: Django :: 5.2
Classifier: Intended Audience :: Developers
Classifier: Natural Language :: English
Classifier: Operating System :: OS Independent
Classifier: Programming Language :: Python
Classifier: Programming Language :: Python :: 3
Classifier: Programming Language :: Python :: 3.11
Classifier: Programming Language :: Python :: 3.12
Classifier: Programming Language :: Python :: 3.13
Classifier: Topic :: Software Development :: Libraries :: Python Modules
Classifier: Topic :: Internet :: WWW/HTTP :: Dynamic Content
Classifier: Topic :: Software Development :: Libraries :: Application Frameworks
Requires-Python: >=3.11
License-File: LICENSE.md
Requires-Dist: Django>=4.2
Requires-Dist: cron-converter>=1.2.2
Requires-Dist: django-environ>=0.11.0
Provides-Extra: dev
Requires-Dist: django-stubs>=5.2.2; extra == "dev"
Requires-Dist: django-stubs[compatible-mypy]~=5.2; extra == "dev"
Requires-Dist: pytest; extra == "dev"
Requires-Dist: pytest-cov; extra == "dev"
Requires-Dist: pytest-django; extra == "dev"
Requires-Dist: pytest-mock; extra == "dev"
Requires-Dist: pytest-randomly; extra == "dev"
Requires-Dist: pytest-xdist; extra == "dev"
Requires-Dist: ruff; extra == "dev"
Requires-Dist: types-python-dateutil; extra == "dev"
Requires-Dist: ipython; extra == "dev"
Requires-Dist: factory_boy; extra == "dev"
Requires-Dist: time-machine; extra == "dev"
Requires-Dist: django-debug-toolbar; extra == "dev"
Requires-Dist: django-extensions; extra == "dev"
Requires-Dist: psycopg[binary]~=3.2; extra == "dev"
Requires-Dist: coverage; extra == "dev"
Requires-Dist: pre-commit; extra == "dev"
Requires-Dist: sphinx; extra == "dev"
Requires-Dist: sphinx-rtd-theme; extra == "dev"
Provides-Extra: redis
Requires-Dist: redis>=5.0.0; extra == "redis"
Requires-Dist: django-redis>=5.4.0; extra == "redis"
Provides-Extra: postgresql
Requires-Dist: psycopg2-binary>=2.9.0; extra == "postgresql"
Provides-Extra: publishing
Requires-Dist: build; extra == "publishing"
Requires-Dist: twine; extra == "publishing"
Dynamic: license-file
